bio_crayon/__init__.py
bio_crayon/core.py
bio_crayon/utils.py
bio_crayon/validators.py
bio_crayon/builtin_colormaps/__init__.py
bio_crayon/schemas/colormap_schema.json
bio_crayon-0.1.3.dist-info/licenses/LICENSE
bio_crayon-0.1.3.dist-info/METADATA
bio_crayon-0.1.3.dist-info/WHEEL
bio_crayon-0.1.3.dist-info/entry_points.txt
bio_crayon-0.1.3.dist-info/top_level.txt
bio_crayon-0.1.3.dist-info/RECORD
